Metadata-Version: 1.0
Name: nl-fsearch
Version: 0.0.2
Summary: A file/folder lookup tool for use with fzf.
Home-page: https://github.com/NonLogicalDev/cli.fsearch
Author: nonlogicaldev
Author-email: UNKNOWN
License: MIT
Platform: UNKNOWN
